CHANGELOG.md
LICENSE
avtomat_aws/__init__.py
avtomat_aws/cli/__init__.py
avtomat_aws/cli/backup/create_backups.py
avtomat_aws/cli/backup/delete_backups.py
avtomat_aws/cli/cloudtrail/discover_events.py
avtomat_aws/cli/cloudtrail/discover_resource_events.py
avtomat_aws/cli/cloudtrail/discover_user_events.py
avtomat_aws/cli/ec2/copy_snapshots.py
avtomat_aws/cli/ec2/create_images.py
avtomat_aws/cli/ec2/create_snapshots.py
avtomat_aws/cli/ec2/delete_images.py
avtomat_aws/cli/ec2/delete_instances.py
avtomat_aws/cli/ec2/delete_security_groups.py
avtomat_aws/cli/ec2/delete_snapshots.py
avtomat_aws/cli/ec2/delete_volumes.py
avtomat_aws/cli/ec2/discover_active_regions.py
avtomat_aws/cli/ec2/discover_default_ebs_encryption.py
avtomat_aws/cli/ec2/discover_images.py
avtomat_aws/cli/ec2/discover_instances.py
avtomat_aws/cli/ec2/discover_no_ssm_instances.py
avtomat_aws/cli/ec2/discover_snapshots.py
avtomat_aws/cli/ec2/discover_tags.py
avtomat_aws/cli/ec2/discover_unused_security_groups.py
avtomat_aws/cli/ec2/discover_volumes.py
avtomat_aws/cli/ec2/encrypt_instance_volumes.py
avtomat_aws/cli/ec2/encrypt_volume.py
avtomat_aws/cli/ec2/modify_default_ebs_encryption.py
avtomat_aws/cli/ec2/modify_tags.py
avtomat_aws/cli/ec2/modify_volumes.py
avtomat_aws/cli/ec2/share_snapshots.py
avtomat_aws/cli/general/get_date.py
avtomat_aws/cli/iam/discover_inactive_console_users.py
avtomat_aws/cli/iam/discover_inactive_users.py
avtomat_aws/cli/iam/discover_no_mfa_users.py
avtomat_aws/cli/iam/discover_old_access_keys.py
avtomat_aws/cli/iam/discover_old_password_users.py
avtomat_aws/cli/iam/discover_permissive_inline_policies.py
avtomat_aws/cli/iam/discover_permissive_policies.py
avtomat_aws/cli/iam/discover_unused_access_keys.py
avtomat_aws/cli/iam/discover_unused_roles.py
avtomat_aws/cli/iam/modify_access_keys.py
avtomat_aws/cli/iam/modify_users_console_access.py
avtomat_aws/cli/iam/quarantine_user.py
avtomat_aws/cli/main.py
avtomat_aws/cli/s3/create_objects.py
avtomat_aws/cli/s3/delete_objects.py
avtomat_aws-0.3.0.dist-info/LICENSE
avtomat_aws-0.3.0.dist-info/METADATA
avtomat_aws-0.3.0.dist-info/WHEEL
avtomat_aws-0.3.0.dist-info/entry_points.txt
avtomat_aws-0.3.0.dist-info/RECORD
