Metadata-Version: 2.1
Name: avtomat-aws
Version: 0.3.0
Summary: A collection of reusable Amazon Web Services actions, bringing speed and certainty to cloud operations.
Home-page: https://avtomat.io
License: GPL-2.0-only
Keywords: aws,cloud,automation,cli,python,boto3
Author: Dimitar Atanasov
Author-email: dimitar@avtomat.io
Requires-Python: >=3.9,<4.0
Classifier: Development Status :: 3 - Alpha
Classifier: Environment :: Console
Classifier: Intended Audience :: Developers
Classifier: Intended Audience :: Information Technology
Classifier: License :: OSI Approved :: GNU General Public License v2 (GPLv2)
Classifier: Natural Language :: English
Classifier: Operating System :: OS Independent
Classifier: Programming Language :: Python
Classifier: Programming Language :: Python :: 3
Classifier: Programming Language :: Python :: 3.9
Classifier: Programming Language :: Python :: 3.10
Classifier: Programming Language :: Python :: 3.11
Classifier: Programming Language :: Python :: 3.12
Classifier: Programming Language :: Python :: 3.13
Requires-Dist: boto3 (>=1.34,<2.0)
Project-URL: Bug Tracker, https://github.com/avtomat-hub/avtomat-aws/issues
Project-URL: Documentation, https://docs.avtomat.io/aws/get_started
Project-URL: GitHub, https://github.com/avtomat-hub/avtomat-aws
